{ "tabela" : { "nome" : "PCINTEGRACAOROTASERVICO", "campos" : [{"nome" : "ID", "valor" : "48"},{"nome" : "IDEMPRESAAPI", "valor" : "4"},{"nome" : "SERVICO", "valor" : "PDV-SYNC - Enviar ICMS"},{"nome" : "LAYOUTCOMUNICACAO", "valor" : {
	"name": "Enviar ICMS",
	"request": {
		"method": "POST",
		"header": [
			{"key": "Authorization", "value": "Bearer {{TOKEN}}"},
			{
				"key": "Accept",
				"value": "*/*"
			},
			{
				"key": "Content-Type",
				"value": "application/json"
			}
		],
		"url": {
			"raw": "{{URL_ENVIAR_ICMS}}",
			"query": []
		},
		"bodyraw": "{{CLIENT_JSON}}"
	}
}},{"nome" : "LAYOUTTRANSFORMACAO", "valor" : [
	{
		"operation": "default",
		"spec": {
			"status": "2"
		}
	}
]},{"nome" : "ATIVO", "valor" : "N"},{"nome" : "AUTENTICADOR", "valor" : "N"},{"nome" : "DATASINCRONISMO", "valor" : "29-JAN-22"},{"nome" : "REFRESHTOKEN", "valor" : "N"},{"nome" : "WINTHORPAGINACAO", "valor" : "N"} ] }, "versaoArquivo" : "1.0.0", "nomeArquivo" : "teste" }
