{ "tabela" : { "nome" : "PCINTEGRACAOROTASERVICO", "campos" : [{"nome" : "ID", "valor" : "71"},{"nome" : "IDEMPRESAAPI", "valor" : "4"},{"nome" : "SERVICO", "valor" : "PDVSync -Atualizar status caixa"},{"nome" : "LAYOUTCOMUNICACAO", "valor" : {
    "name": "PDVSync - atualizar status caixa",
    "request": {
        "method": "PUT",
        "header": [
            {"key": "Authorization", "value": "Bearer {{TOKEN}}"}, 
			{
				"key": "Accept",
				"value": "*/*"
			},
			{
				"key": "Content-Type",
				"value": "application/json"
			}
        ],
        "url": {
            "raw": "{{URL_ATUALIZAR_STATUS_CAIXA}}",
            "query": []
        },
        "bodyraw": [{ "idMensagem": "{{ID_MENSAGEM}}",  "status": "{{STATUS_INTEGRACAO}}" }]
    },
    "response": []
}},{"nome" : "LAYOUTTRANSFORMACAO", "valor" : [
		{
			"operation": "default",
			"spec": {
				"status": 2
			}
		}
]
	},{"nome" : "ATIVO", "valor" : "S"},{"nome" : "AUTENTICADOR", "valor" : "N"},{"nome" : "DATASINCRONISMO", "valor" : ""},{"nome" : "REFRESHTOKEN", "valor" : ""},{"nome" : "WINTHORPAGINACAO", "valor" : "N"} ] }, "versaoArquivo" : "1.0.0", "nomeArquivo" : "teste" }
